COPYING.txt
MANIFEST.in
setup.py
libK/__init__.py
libK/agree.py
libK/array_to_table.py
libK/conv_date.py
libK/curl.py
libK/db.py
libK/diff.py
libK/ftp.py
libK/get_kernel.py
libK/in_work.py
libK/kernel.py
libK/mail.py
libK/md.py
libK/parallel.py
libK/sftp.py
libK/shell.py
libK/ssh.py
libK.egg-info/PKG-INFO
libK.egg-info/SOURCES.txt
libK.egg-info/dependency_links.txt
libK.egg-info/top_level.txt