Metadata-Version: 1.0
Name: libK
Version: 0.0.29
Summary: Lib for fast coding
Home-page: https://bitbucket.org/Negash/libk
Author: Negash
Author-email: i@negash.ru
License: UNKNOWN
Platform: UNKNOWN
